{
  "lastUpdated": "2026-02-14",
  "incidents": [
    {
      "id": "INC-2024-053",
      "driverId": "oscar-piastri",
      "teamId": "mclaren",
      "round": 21,
      "season": 2024,
      "raceName": "São Paulo Grand Prix",
      "date": "2024-11-03",
      "session": "Race",
      "incidentType": "causing-collision",
      "incidentDescription": "Caused collision at Turn 1 on lap 1 — incident under investigation post-race",
      "decision": {
        "penaltyPoints": 2,
        "timePenalty": 10,
        "gridPenalty": null,
        "driveThrough": false,
        "reprimand": false,
        "disqualified": false,
        "fine": null,
        "other": null
      },
      "document": "DOC-2024-053"
    },
    {
      "id": "INC-2024-048",
      "driverId": "lance-stroll",
      "teamId": "aston-martin",
      "round": 22,
      "season": 2024,
      "raceName": "Las Vegas Grand Prix",
      "date": "2024-11-23",
      "session": "Race",
      "incidentType": "causing-collision",
      "incidentDescription": "Caused collision with Nico Hulkenberg at Turn 14 on lap 38",
      "decision": {
        "penaltyPoints": 2,
        "timePenalty": 5,
        "gridPenalty": null,
        "driveThrough": false,
        "reprimand": false,
        "disqualified": false,
        "fine": null,
        "other": null
      },
      "document": "DOC-2024-048"
    },
    {
      "id": "INC-2024-051",
      "driverId": "sergio-perez",
      "teamId": "red-bull",
      "round": 23,
      "season": 2024,
      "raceName": "Qatar Grand Prix",
      "date": "2024-12-01",
      "session": "Race",
      "incidentType": "unsafe-release",
      "incidentDescription": "Unsafe release from pit box into the path of Pierre Gasly",
      "decision": {
        "penaltyPoints": 2,
        "timePenalty": 5,
        "gridPenalty": null,
        "driveThrough": false,
        "reprimand": false,
        "disqualified": false,
        "fine": null,
        "other": null
      },
      "document": "DOC-2024-051"
    },
    {
      "id": "INC-2024-057",
      "driverId": "lance-stroll",
      "teamId": "aston-martin",
      "round": 23,
      "season": 2024,
      "raceName": "Qatar Grand Prix",
      "date": "2024-12-01",
      "session": "Race",
      "incidentType": "causing-collision",
      "incidentDescription": "Caused collision with Alex Albon at Turn 1 on lap 15",
      "decision": {
        "penaltyPoints": 2,
        "timePenalty": 10,
        "gridPenalty": null,
        "driveThrough": false,
        "reprimand": false,
        "disqualified": false,
        "fine": null,
        "other": null
      },
      "document": "DOC-2024-057"
    },
    {
      "id": "INC-2024-058",
      "driverId": "liam-lawson",
      "teamId": "racing-bulls",
      "round": 23,
      "season": 2024,
      "raceName": "Qatar Grand Prix",
      "date": "2024-12-01",
      "session": "Race",
      "incidentType": "causing-collision",
      "incidentDescription": "Caused collision with Valtteri Bottas at Turn 1 on lap 15",
      "decision": {
        "penaltyPoints": 2,
        "timePenalty": 10,
        "gridPenalty": null,
        "driveThrough": false,
        "reprimand": false,
        "disqualified": false,
        "fine": null,
        "other": null
      },
      "document": "DOC-2024-058"
    },
    {
      "id": "INC-2024-050",
      "driverId": "max-verstappen",
      "teamId": "red-bull",
      "round": 24,
      "season": 2024,
      "raceName": "Abu Dhabi Grand Prix",
      "date": "2024-12-08",
      "session": "Race",
      "incidentType": "causing-collision",
      "incidentDescription": "Caused collision with Oscar Piastri at Turn 6 on lap 24",
      "decision": {
        "penaltyPoints": 2,
        "timePenalty": 10,
        "gridPenalty": null,
        "driveThrough": false,
        "reprimand": false,
        "disqualified": false,
        "fine": null,
        "other": null
      },
      "document": "DOC-2024-050"
    },
    {
      "id": "INC-2024-052",
      "driverId": "oscar-piastri",
      "teamId": "mclaren",
      "round": 24,
      "season": 2024,
      "raceName": "Abu Dhabi Grand Prix",
      "date": "2024-12-08",
      "session": "Race",
      "incidentType": "causing-collision",
      "incidentDescription": "Caused collision with Franco Colapinto at Turn 9 on lap 35",
      "decision": {
        "penaltyPoints": 2,
        "timePenalty": 5,
        "gridPenalty": null,
        "driveThrough": false,
        "reprimand": false,
        "disqualified": false,
        "fine": null,
        "other": null
      },
      "document": "DOC-2024-052"
    },
    {
      "id": "INC-2024-054",
      "driverId": "oliver-bearman",
      "teamId": "haas",
      "round": 24,
      "season": 2024,
      "raceName": "Abu Dhabi Grand Prix",
      "date": "2024-12-08",
      "session": "Race",
      "incidentType": "forcing-off-track",
      "incidentDescription": "Forced Alex Albon off track at Turn 9 on lap 22",
      "decision": {
        "penaltyPoints": 1,
        "timePenalty": 5,
        "gridPenalty": null,
        "driveThrough": false,
        "reprimand": false,
        "disqualified": false,
        "fine": null,
        "other": null
      },
      "document": "DOC-2024-054"
    },
    {
      "id": "INC-2024-055",
      "driverId": "valtteri-bottas",
      "teamId": "audi",
      "round": 24,
      "season": 2024,
      "raceName": "Abu Dhabi Grand Prix",
      "date": "2024-12-08",
      "session": "Race",
      "incidentType": "causing-collision",
      "incidentDescription": "Caused collision with Sergio Perez at Turn 6 on lap 1 — Perez retired, Virtual Safety Car deployed",
      "decision": {
        "penaltyPoints": 2,
        "timePenalty": 10,
        "gridPenalty": null,
        "driveThrough": false,
        "reprimand": false,
        "disqualified": false,
        "fine": null,
        "other": null
      },
      "document": "DOC-2024-055"
    },
    {
      "id": "INC-2024-056",
      "driverId": "valtteri-bottas",
      "teamId": "audi",
      "round": 24,
      "season": 2024,
      "raceName": "Abu Dhabi Grand Prix",
      "date": "2024-12-08",
      "session": "Race",
      "incidentType": "causing-collision",
      "incidentDescription": "Significant braking misjudgement at Turn 6 on lap 31 — collided with Kevin Magnussen on the racing line, both retired",
      "decision": {
        "penaltyPoints": 3,
        "timePenalty": null,
        "gridPenalty": 5,
        "driveThrough": false,
        "reprimand": false,
        "disqualified": false,
        "fine": null,
        "other": "Grid penalty carries over to first 2026 race (Australian GP with Cadillac)"
      },
      "document": "DOC-2024-056"
    },
    {
      "id": "INC-2025-065",
      "driverId": "jack-doohan",
      "teamId": "alpine",
      "round": 2,
      "season": 2025,
      "raceName": "Chinese Grand Prix",
      "date": "2025-03-23",
      "session": "Sprint",
      "incidentType": "causing-collision",
      "incidentDescription": "Causing a collision with Gabriel Bortoleto",
      "decision": {
        "penaltyPoints": 2,
        "timePenalty": null,
        "gridPenalty": null,
        "driveThrough": false,
        "reprimand": false,
        "disqualified": false,
        "fine": null,
        "other": null
      },
      "document": "DOC-2025-LP"
    },
    {
      "id": "INC-2025-066",
      "driverId": "jack-doohan",
      "teamId": "alpine",
      "round": 2,
      "season": 2025,
      "raceName": "Chinese Grand Prix",
      "date": "2025-03-23",
      "session": "Race",
      "incidentType": "forcing-off-track",
      "incidentDescription": "Forcing Isack Hadjar off the track",
      "decision": {
        "penaltyPoints": 2,
        "timePenalty": null,
        "gridPenalty": null,
        "driveThrough": false,
        "reprimand": false,
        "disqualified": false,
        "fine": null,
        "other": null
      },
      "document": "DOC-2025-LP"
    },
    {
      "id": "INC-2025-004",
      "driverId": "nico-hulkenberg",
      "teamId": "audi",
      "round": 3,
      "season": 2025,
      "raceName": "Japanese Grand Prix",
      "date": "2025-04-06",
      "session": "Race",
      "incidentType": "unsafe-release",
      "incidentDescription": "Unsafe release from pit box impeding Carlos Sainz at pit exit",
      "decision": {
        "penaltyPoints": 0,
        "timePenalty": null,
        "gridPenalty": null,
        "driveThrough": false,
        "reprimand": true,
        "disqualified": false,
        "fine": null,
        "other": null
      },
      "document": "DOC-2025-004"
    },
    {
      "id": "INC-2025-001",
      "driverId": "liam-lawson",
      "teamId": "racing-bulls",
      "round": 4,
      "season": 2025,
      "raceName": "Bahrain Grand Prix",
      "date": "2025-04-13",
      "session": "Race",
      "incidentType": "causing-collision",
      "incidentDescription": "Caused collision with Lance Stroll at Turn 4 on lap 18",
      "decision": {
        "penaltyPoints": 1,
        "timePenalty": 5,
        "gridPenalty": null,
        "driveThrough": false,
        "reprimand": false,
        "disqualified": false,
        "fine": null,
        "other": null
      },
      "document": "DOC-2025-001"
    },
    {
      "id": "INC-2025-002",
      "driverId": "liam-lawson",
      "teamId": "racing-bulls",
      "round": 4,
      "season": 2025,
      "raceName": "Bahrain Grand Prix",
      "date": "2025-04-13",
      "session": "Race",
      "incidentType": "causing-collision",
      "incidentDescription": "Caused collision with Nico Hulkenberg on lap 42 at Turn 1",
      "decision": {
        "penaltyPoints": 2,
        "timePenalty": 5,
        "gridPenalty": null,
        "driveThrough": false,
        "reprimand": false,
        "disqualified": false,
        "fine": null,
        "other": null
      },
      "document": "DOC-2025-002"
    },
    {
      "id": "INC-2025-003",
      "driverId": "carlos-sainz",
      "teamId": "williams",
      "round": 4,
      "season": 2025,
      "raceName": "Bahrain Grand Prix",
      "date": "2025-04-13",
      "session": "Race",
      "incidentType": "causing-collision",
      "incidentDescription": "Caused collision with Kimi Antonelli at Turn 10 on lap 27",
      "decision": {
        "penaltyPoints": 2,
        "timePenalty": 10,
        "gridPenalty": null,
        "driveThrough": false,
        "reprimand": false,
        "disqualified": false,
        "fine": null,
        "other": null
      },
      "document": "DOC-2025-003"
    },
    {
      "id": "INC-2025-005",
      "driverId": "max-verstappen",
      "teamId": "red-bull",
      "round": 5,
      "season": 2025,
      "raceName": "Miami Grand Prix",
      "date": "2025-05-03",
      "session": "Sprint",
      "incidentType": "unsafe-release",
      "incidentDescription": "Unsafe pit release resulting in collision with Kimi Antonelli",
      "decision": {
        "penaltyPoints": 0,
        "timePenalty": 10,
        "gridPenalty": null,
        "driveThrough": false,
        "reprimand": false,
        "disqualified": false,
        "fine": null,
        "other": "Team error — penalty applied to driver's race time"
      },
      "document": "DOC-2025-005"
    },
    {
      "id": "INC-2025-006",
      "driverId": "liam-lawson",
      "teamId": "racing-bulls",
      "round": 5,
      "season": 2025,
      "raceName": "Miami Grand Prix",
      "date": "2025-05-03",
      "session": "Sprint",
      "incidentType": "causing-collision",
      "incidentDescription": "Caused collision with Fernando Alonso at Turn 1 on lap 1",
      "decision": {
        "penaltyPoints": 1,
        "timePenalty": 5,
        "gridPenalty": null,
        "driveThrough": false,
        "reprimand": false,
        "disqualified": false,
        "fine": null,
        "other": null
      },
      "document": "DOC-2025-006"
    },
    {
      "id": "INC-2025-007",
      "driverId": "oliver-bearman",
      "teamId": "haas",
      "round": 7,
      "season": 2025,
      "raceName": "Monaco Grand Prix",
      "date": "2025-05-23",
      "session": "FP2",
      "incidentType": "red-flag-infringement",
      "incidentDescription": "Overtook Carlos Sainz under red flag conditions during practice at the Swimming Pool section",
      "decision": {
        "penaltyPoints": 2,
        "timePenalty": null,
        "gridPenalty": 10,
        "driveThrough": false,
        "reprimand": false,
        "disqualified": false,
        "fine": null,
        "other": null
      },
      "document": "DOC-2025-007"
    },
    {
      "id": "INC-2025-008",
      "driverId": "lance-stroll",
      "teamId": "aston-martin",
      "round": 7,
      "season": 2025,
      "raceName": "Monaco Grand Prix",
      "date": "2025-05-23",
      "session": "FP1",
      "incidentType": "causing-collision",
      "incidentDescription": "Collided with Charles Leclerc at Sainte Devote during practice",
      "decision": {
        "penaltyPoints": 1,
        "timePenalty": null,
        "gridPenalty": null,
        "driveThrough": false,
        "reprimand": true,
        "disqualified": false,
        "fine": null,
        "other": null
      },
      "document": "DOC-2025-008"
    },
    {
      "id": "INC-2025-009",
      "driverId": "lewis-hamilton",
      "teamId": "ferrari",
      "round": 7,
      "season": 2025,
      "raceName": "Monaco Grand Prix",
      "date": "2025-05-24",
      "session": "Qualifying",
      "incidentType": "impeding",
      "incidentDescription": "Impeded Max Verstappen in Q1 at Rascasse — team miscommunication",
      "decision": {
        "penaltyPoints": 0,
        "timePenalty": null,
        "gridPenalty": 3,
        "driveThrough": false,
        "reprimand": false,
        "disqualified": false,
        "fine": null,
        "other": null
      },
      "document": "DOC-2025-009"
    },
    {
      "id": "INC-2025-010",
      "driverId": "max-verstappen",
      "teamId": "red-bull",
      "round": 8,
      "season": 2025,
      "raceName": "Spanish Grand Prix",
      "date": "2025-06-01",
      "session": "Race",
      "incidentType": "causing-collision",
      "incidentDescription": "Collided with George Russell on lap 64 at Turn 5 — dropped from P5 to P10",
      "decision": {
        "penaltyPoints": 3,
        "timePenalty": 10,
        "gridPenalty": null,
        "driveThrough": false,
        "reprimand": false,
        "disqualified": false,
        "fine": null,
        "other": null
      },
      "document": "DOC-2025-010"
    },
    {
      "id": "INC-2025-011",
      "driverId": "lance-stroll",
      "teamId": "aston-martin",
      "round": 9,
      "season": 2025,
      "raceName": "Canadian Grand Prix",
      "date": "2025-06-15",
      "session": "Race",
      "incidentType": "forcing-off-track",
      "incidentDescription": "Pushed Pierre Gasly off track at Turn 3 on lap 31",
      "decision": {
        "penaltyPoints": 2,
        "timePenalty": 10,
        "gridPenalty": null,
        "driveThrough": false,
        "reprimand": false,
        "disqualified": false,
        "fine": null,
        "other": null
      },
      "document": "DOC-2025-011"
    },
    {
      "id": "INC-2025-060",
      "driverId": "yuki-tsunoda",
      "teamId": "racing-bulls",
      "round": 9,
      "season": 2025,
      "raceName": "Canadian Grand Prix",
      "date": "2025-06-15",
      "session": "FP3",
      "incidentType": "red-flag-infringement",
      "incidentDescription": "Overtaking Oscar Piastri during red flag conditions",
      "decision": {
        "penaltyPoints": 2,
        "timePenalty": null,
        "gridPenalty": null,
        "driveThrough": false,
        "reprimand": false,
        "disqualified": false,
        "fine": null,
        "other": null
      },
      "document": "DOC-2025-LP"
    },
    {
      "id": "INC-2025-012",
      "driverId": "kimi-antonelli",
      "teamId": "mercedes",
      "round": 10,
      "season": 2025,
      "raceName": "Austrian Grand Prix",
      "date": "2025-06-29",
      "session": "Race",
      "incidentType": "causing-collision",
      "incidentDescription": "Collided with Max Verstappen on lap 1 at Turn 3",
      "decision": {
        "penaltyPoints": 2,
        "timePenalty": null,
        "gridPenalty": 3,
        "driveThrough": false,
        "reprimand": false,
        "disqualified": false,
        "fine": null,
        "other": "Grid penalty applied to British Grand Prix"
      },
      "document": "DOC-2025-012"
    },
    {
      "id": "INC-2025-013",
      "driverId": "franco-colapinto",
      "teamId": "alpine",
      "round": 10,
      "season": 2025,
      "raceName": "Austrian Grand Prix",
      "date": "2025-06-29",
      "session": "Race",
      "incidentType": "forcing-off-track",
      "incidentDescription": "Forced Oscar Piastri off track while being lapped at Turn 4",
      "decision": {
        "penaltyPoints": 1,
        "timePenalty": 5,
        "gridPenalty": null,
        "driveThrough": false,
        "reprimand": false,
        "disqualified": false,
        "fine": null,
        "other": null
      },
      "document": "DOC-2025-013"
    },
    {
      "id": "INC-2025-061",
      "driverId": "yuki-tsunoda",
      "teamId": "racing-bulls",
      "round": 10,
      "season": 2025,
      "raceName": "Austrian Grand Prix",
      "date": "2025-06-29",
      "session": "Race",
      "incidentType": "causing-collision",
      "incidentDescription": "Causing a collision with Franco Colapinto",
      "decision": {
        "penaltyPoints": 2,
        "timePenalty": null,
        "gridPenalty": null,
        "driveThrough": false,
        "reprimand": false,
        "disqualified": false,
        "fine": null,
        "other": null
      },
      "document": "DOC-2025-LP"
    },
    {
      "id": "INC-2025-014",
      "driverId": "oliver-bearman",
      "teamId": "haas",
      "round": 11,
      "season": 2025,
      "raceName": "British Grand Prix",
      "date": "2025-07-05",
      "session": "FP3",
      "incidentType": "pit-entry-infringement",
      "incidentDescription": "Crashed at pit entry under red flag conditions during practice — extremely dangerous incident",
      "decision": {
        "penaltyPoints": 4,
        "timePenalty": null,
        "gridPenalty": 10,
        "driveThrough": false,
        "reprimand": false,
        "disqualified": false,
        "fine": null,
        "other": null
      },
      "document": "DOC-2025-014"
    },
    {
      "id": "INC-2025-015",
      "driverId": "oscar-piastri",
      "teamId": "mclaren",
      "round": 11,
      "season": 2025,
      "raceName": "British Grand Prix",
      "date": "2025-07-06",
      "session": "Race",
      "incidentType": "safety-car-infringement",
      "incidentDescription": "Erratic braking on straight before safety car restart — dropped from 218 km/h to 52 km/h mid-straight",
      "decision": {
        "penaltyPoints": 2,
        "timePenalty": 10,
        "gridPenalty": null,
        "driveThrough": false,
        "reprimand": false,
        "disqualified": false,
        "fine": null,
        "other": "Cost him the win — dropped to P4"
      },
      "document": "DOC-2025-015"
    },
    {
      "id": "INC-2025-062",
      "driverId": "yuki-tsunoda",
      "teamId": "racing-bulls",
      "round": 11,
      "season": 2025,
      "raceName": "British Grand Prix",
      "date": "2025-07-06",
      "session": "Race",
      "incidentType": "causing-collision",
      "incidentDescription": "Causing a collision with Oliver Bearman",
      "decision": {
        "penaltyPoints": 1,
        "timePenalty": null,
        "gridPenalty": null,
        "driveThrough": false,
        "reprimand": false,
        "disqualified": false,
        "fine": null,
        "other": null
      },
      "document": "DOC-2025-LP"
    },
    {
      "id": "INC-2025-016",
      "driverId": "charles-leclerc",
      "teamId": "ferrari",
      "round": 13,
      "season": 2025,
      "raceName": "Hungarian Grand Prix",
      "date": "2025-08-03",
      "session": "Race",
      "incidentType": "change-of-direction",
      "incidentDescription": "Moving under braking while defending from George Russell at Turn 1",
      "decision": {
        "penaltyPoints": 1,
        "timePenalty": 5,
        "gridPenalty": null,
        "driveThrough": false,
        "reprimand": false,
        "disqualified": false,
        "fine": null,
        "other": null
      },
      "document": "DOC-2025-016"
    },
    {
      "id": "INC-2025-017",
      "driverId": "pierre-gasly",
      "teamId": "alpine",
      "round": 13,
      "season": 2025,
      "raceName": "Hungarian Grand Prix",
      "date": "2025-08-03",
      "session": "Race",
      "incidentType": "causing-collision",
      "incidentDescription": "Caused collision with Carlos Sainz at Turn 4 on lap 38",
      "decision": {
        "penaltyPoints": 2,
        "timePenalty": 10,
        "gridPenalty": null,
        "driveThrough": false,
        "reprimand": false,
        "disqualified": false,
        "fine": null,
        "other": null
      },
      "document": "DOC-2025-017"
    },
    {
      "id": "INC-2025-018",
      "driverId": "carlos-sainz",
      "teamId": "williams",
      "round": 14,
      "season": 2025,
      "raceName": "Dutch Grand Prix",
      "date": "2025-08-31",
      "session": "Race",
      "incidentType": "causing-collision",
      "incidentDescription": "Collision with Liam Lawson at Turn 1 — penalty rescinded after Williams appeal on Sep 13",
      "decision": {
        "penaltyPoints": 0,
        "timePenalty": null,
        "gridPenalty": null,
        "driveThrough": false,
        "reprimand": false,
        "disqualified": false,
        "fine": null,
        "other": "Original 10s penalty + 2 pts rescinded — stewards determined Lawson lost control"
      },
      "document": "DOC-2025-018"
    },
    {
      "id": "INC-2025-019",
      "driverId": "kimi-antonelli",
      "teamId": "mercedes",
      "round": 14,
      "season": 2025,
      "raceName": "Dutch Grand Prix",
      "date": "2025-08-31",
      "session": "Race",
      "incidentType": "causing-collision",
      "incidentDescription": "Collided with Charles Leclerc at Turn 1 on lap 3",
      "decision": {
        "penaltyPoints": 2,
        "timePenalty": 10,
        "gridPenalty": null,
        "driveThrough": false,
        "reprimand": false,
        "disqualified": false,
        "fine": null,
        "other": null
      },
      "document": "DOC-2025-019"
    },
    {
      "id": "INC-2025-020",
      "driverId": "lewis-hamilton",
      "teamId": "ferrari",
      "round": 14,
      "season": 2025,
      "raceName": "Dutch Grand Prix",
      "date": "2025-08-31",
      "session": "Pre-Race",
      "incidentType": "dangerous-driving",
      "incidentDescription": "Drove unnecessarily slowly during pre-race reconnaissance laps, creating a dangerous situation on track",
      "decision": {
        "penaltyPoints": 2,
        "timePenalty": null,
        "gridPenalty": 5,
        "driveThrough": false,
        "reprimand": false,
        "disqualified": false,
        "fine": null,
        "other": "Grid penalty applied to Italian Grand Prix"
      },
      "document": "DOC-2025-020"
    },
    {
      "id": "INC-2025-021",
      "driverId": "kimi-antonelli",
      "teamId": "mercedes",
      "round": 14,
      "season": 2025,
      "raceName": "Dutch Grand Prix",
      "date": "2025-08-31",
      "session": "Race",
      "incidentType": "speeding-pit-lane",
      "incidentDescription": "Exceeded pit lane speed limit by 4 km/h during pit stop on lap 28",
      "decision": {
        "penaltyPoints": 0,
        "timePenalty": 5,
        "gridPenalty": null,
        "driveThrough": false,
        "reprimand": false,
        "disqualified": false,
        "fine": null,
        "other": null
      },
      "document": "DOC-2025-021"
    },
    {
      "id": "INC-2025-022",
      "driverId": "oliver-bearman",
      "teamId": "haas",
      "round": 15,
      "season": 2025,
      "raceName": "Italian Grand Prix",
      "date": "2025-09-07",
      "session": "Race",
      "incidentType": "causing-collision",
      "incidentDescription": "Rear-ended Carlos Sainz at the Variante del Rettifilo chicane on lap 19",
      "decision": {
        "penaltyPoints": 2,
        "timePenalty": 10,
        "gridPenalty": null,
        "driveThrough": false,
        "reprimand": false,
        "disqualified": false,
        "fine": null,
        "other": null
      },
      "document": "DOC-2025-022"
    },
    {
      "id": "INC-2025-023",
      "driverId": "kimi-antonelli",
      "teamId": "mercedes",
      "round": 15,
      "season": 2025,
      "raceName": "Italian Grand Prix",
      "date": "2025-09-07",
      "session": "Race",
      "incidentType": "dangerous-driving",
      "incidentDescription": "Erratic driving in battle with Alex Albon at Curva Grande — weaving under braking",
      "decision": {
        "penaltyPoints": 1,
        "timePenalty": 5,
        "gridPenalty": null,
        "driveThrough": false,
        "reprimand": false,
        "disqualified": false,
        "fine": null,
        "other": null
      },
      "document": "DOC-2025-023"
    },
    {
      "id": "INC-2025-042",
      "driverId": "esteban-ocon",
      "teamId": "haas",
      "round": 15,
      "season": 2025,
      "raceName": "Italian Grand Prix",
      "date": "2025-09-07",
      "session": "Race",
      "incidentType": "forcing-off-track",
      "incidentDescription": "Forced Lance Stroll off track at the Variante della Roggia chicane on lap 2",
      "decision": {
        "penaltyPoints": 1,
        "timePenalty": 5,
        "gridPenalty": null,
        "driveThrough": false,
        "reprimand": false,
        "disqualified": false,
        "fine": null,
        "other": null
      },
      "document": "DOC-2025-042"
    },
    {
      "id": "INC-2025-024",
      "driverId": "alex-albon",
      "teamId": "williams",
      "round": 16,
      "season": 2025,
      "raceName": "Azerbaijan Grand Prix",
      "date": "2025-09-21",
      "session": "Race",
      "incidentType": "causing-collision",
      "incidentDescription": "Caused collision with Franco Colapinto at Turn 5 on lap 16",
      "decision": {
        "penaltyPoints": 2,
        "timePenalty": 10,
        "gridPenalty": null,
        "driveThrough": false,
        "reprimand": false,
        "disqualified": false,
        "fine": null,
        "other": null
      },
      "document": "DOC-2025-024"
    },
    {
      "id": "INC-2025-025",
      "driverId": "fernando-alonso",
      "teamId": "aston-martin",
      "round": 16,
      "season": 2025,
      "raceName": "Azerbaijan Grand Prix",
      "date": "2025-09-21",
      "session": "Race",
      "incidentType": "false-start",
      "incidentDescription": "False start — reacted to Piastri's movement on the grid",
      "decision": {
        "penaltyPoints": 0,
        "timePenalty": 5,
        "gridPenalty": null,
        "driveThrough": false,
        "reprimand": false,
        "disqualified": false,
        "fine": null,
        "other": null
      },
      "document": "DOC-2025-025"
    },
    {
      "id": "INC-2025-026",
      "driverId": "lance-stroll",
      "teamId": "aston-martin",
      "round": 18,
      "season": 2025,
      "raceName": "United States Grand Prix",
      "date": "2025-10-18",
      "session": "Sprint",
      "incidentType": "causing-collision",
      "incidentDescription": "Caused collision with Esteban Ocon at Turn 12 on lap 8",
      "decision": {
        "penaltyPoints": 2,
        "timePenalty": null,
        "gridPenalty": 5,
        "driveThrough": false,
        "reprimand": false,
        "disqualified": false,
        "fine": null,
        "other": "Grid penalty applied to United States Grand Prix race"
      },
      "document": "DOC-2025-026"
    },
    {
      "id": "INC-2025-027",
      "driverId": "carlos-sainz",
      "teamId": "williams",
      "round": 18,
      "season": 2025,
      "raceName": "United States Grand Prix",
      "date": "2025-10-19",
      "session": "Race",
      "incidentType": "causing-collision",
      "incidentDescription": "Caused collision with Kimi Antonelli at Turn 15 on lap 46",
      "decision": {
        "penaltyPoints": 2,
        "timePenalty": null,
        "gridPenalty": 5,
        "driveThrough": false,
        "reprimand": false,
        "disqualified": false,
        "fine": null,
        "other": null
      },
      "document": "DOC-2025-027"
    },
    {
      "id": "INC-2025-028",
      "driverId": "sergio-perez",
      "teamId": "red-bull",
      "round": 19,
      "season": 2025,
      "raceName": "Mexico City Grand Prix",
      "date": "2025-10-26",
      "session": "Race",
      "incidentType": "track-limits",
      "incidentDescription": "Exceeded track limits multiple times at Turn 5 — 5 violations",
      "decision": {
        "penaltyPoints": 0,
        "timePenalty": 10,
        "gridPenalty": null,
        "driveThrough": false,
        "reprimand": false,
        "disqualified": false,
        "fine": null,
        "other": null
      },
      "document": "DOC-2025-028"
    },
    {
      "id": "INC-2025-029",
      "driverId": "nico-hulkenberg",
      "teamId": "audi",
      "round": 19,
      "season": 2025,
      "raceName": "Mexico City Grand Prix",
      "date": "2025-10-26",
      "session": "Race",
      "incidentType": "track-limits",
      "incidentDescription": "Repeated track limit violations at Turn 5 — 4 infractions",
      "decision": {
        "penaltyPoints": 0,
        "timePenalty": 5,
        "gridPenalty": null,
        "driveThrough": false,
        "reprimand": false,
        "disqualified": false,
        "fine": null,
        "other": null
      },
      "document": "DOC-2025-029"
    },
    {
      "id": "INC-2025-030",
      "driverId": "oliver-bearman",
      "teamId": "haas",
      "round": 20,
      "season": 2025,
      "raceName": "São Paulo Grand Prix",
      "date": "2025-11-08",
      "session": "Sprint",
      "incidentType": "causing-collision",
      "incidentDescription": "Collided with Liam Lawson at Turn 4 on lap 15",
      "decision": {
        "penaltyPoints": 1,
        "timePenalty": 5,
        "gridPenalty": null,
        "driveThrough": false,
        "reprimand": false,
        "disqualified": false,
        "fine": null,
        "other": null
      },
      "document": "DOC-2025-030"
    },
    {
      "id": "INC-2025-031",
      "driverId": "liam-lawson",
      "teamId": "racing-bulls",
      "round": 20,
      "season": 2025,
      "raceName": "São Paulo Grand Prix",
      "date": "2025-11-08",
      "session": "Sprint",
      "incidentType": "causing-collision",
      "incidentDescription": "Collided with Oliver Bearman at Turn 4 on lap 15",
      "decision": {
        "penaltyPoints": 1,
        "timePenalty": 5,
        "gridPenalty": null,
        "driveThrough": false,
        "reprimand": false,
        "disqualified": false,
        "fine": null,
        "other": null
      },
      "document": "DOC-2025-031"
    },
    {
      "id": "INC-2025-032",
      "driverId": "oscar-piastri",
      "teamId": "mclaren",
      "round": 20,
      "season": 2025,
      "raceName": "São Paulo Grand Prix",
      "date": "2025-11-09",
      "session": "Race",
      "incidentType": "causing-collision",
      "incidentDescription": "Caused collision with Kimi Antonelli at Turn 1 on lap 22",
      "decision": {
        "penaltyPoints": 2,
        "timePenalty": 10,
        "gridPenalty": null,
        "driveThrough": false,
        "reprimand": false,
        "disqualified": false,
        "fine": null,
        "other": null
      },
      "document": "DOC-2025-032"
    },
    {
      "id": "INC-2025-033",
      "driverId": "lewis-hamilton",
      "teamId": "ferrari",
      "round": 20,
      "season": 2025,
      "raceName": "São Paulo Grand Prix",
      "date": "2025-11-09",
      "session": "Race",
      "incidentType": "causing-collision",
      "incidentDescription": "Caused collision with Franco Colapinto at Turn 15 on lap 2",
      "decision": {
        "penaltyPoints": 1,
        "timePenalty": 5,
        "gridPenalty": null,
        "driveThrough": false,
        "reprimand": false,
        "disqualified": false,
        "fine": null,
        "other": null
      },
      "document": "DOC-2025-033"
    },
    {
      "id": "INC-2025-063",
      "driverId": "yuki-tsunoda",
      "teamId": "racing-bulls",
      "round": 20,
      "season": 2025,
      "raceName": "São Paulo Grand Prix",
      "date": "2025-11-09",
      "session": "Race",
      "incidentType": "causing-collision",
      "incidentDescription": "Causing a collision with Lance Stroll",
      "decision": {
        "penaltyPoints": 2,
        "timePenalty": null,
        "gridPenalty": null,
        "driveThrough": false,
        "reprimand": false,
        "disqualified": false,
        "fine": null,
        "other": null
      },
      "document": "DOC-2025-LP"
    },
    {
      "id": "INC-2025-034",
      "driverId": "lando-norris",
      "teamId": "mclaren",
      "round": 21,
      "season": 2025,
      "raceName": "Las Vegas Grand Prix",
      "date": "2025-11-23",
      "session": "Race",
      "incidentType": "technical-violation",
      "incidentDescription": "Excessive plank wear — skid block measured at 8.88mm (minimum 9mm)",
      "decision": {
        "penaltyPoints": 0,
        "timePenalty": null,
        "gridPenalty": null,
        "driveThrough": false,
        "reprimand": false,
        "disqualified": true,
        "fine": null,
        "other": null
      },
      "document": "DOC-2025-034"
    },
    {
      "id": "INC-2025-035",
      "driverId": "oscar-piastri",
      "teamId": "mclaren",
      "round": 21,
      "season": 2025,
      "raceName": "Las Vegas Grand Prix",
      "date": "2025-11-23",
      "session": "Race",
      "incidentType": "technical-violation",
      "incidentDescription": "Excessive plank wear — skid block measured at 8.74mm (minimum 9mm)",
      "decision": {
        "penaltyPoints": 0,
        "timePenalty": null,
        "gridPenalty": null,
        "driveThrough": false,
        "reprimand": false,
        "disqualified": true,
        "fine": null,
        "other": null
      },
      "document": "DOC-2025-035"
    },
    {
      "id": "INC-2025-036",
      "driverId": "alex-albon",
      "teamId": "williams",
      "round": 21,
      "season": 2025,
      "raceName": "Las Vegas Grand Prix",
      "date": "2025-11-23",
      "session": "Race",
      "incidentType": "causing-collision",
      "incidentDescription": "Caused collision with Lewis Hamilton at Turn 14 on lap 29",
      "decision": {
        "penaltyPoints": 1,
        "timePenalty": 5,
        "gridPenalty": null,
        "driveThrough": false,
        "reprimand": false,
        "disqualified": false,
        "fine": null,
        "other": null
      },
      "document": "DOC-2025-036"
    },
    {
      "id": "INC-2025-037",
      "driverId": "gabriel-bortoleto",
      "teamId": "audi",
      "round": 21,
      "season": 2025,
      "raceName": "Las Vegas Grand Prix",
      "date": "2025-11-23",
      "session": "Race",
      "incidentType": "causing-collision",
      "incidentDescription": "Caused collision with Lance Stroll at Turn 1 on lap 1",
      "decision": {
        "penaltyPoints": 2,
        "timePenalty": null,
        "gridPenalty": 5,
        "driveThrough": false,
        "reprimand": false,
        "disqualified": false,
        "fine": null,
        "other": "Grid penalty applied to Qatar Grand Prix"
      },
      "document": "DOC-2025-037"
    },
    {
      "id": "INC-2025-038",
      "driverId": "kimi-antonelli",
      "teamId": "mercedes",
      "round": 21,
      "season": 2025,
      "raceName": "Las Vegas Grand Prix",
      "date": "2025-11-23",
      "session": "Race",
      "incidentType": "false-start",
      "incidentDescription": "Moved before lights extinguished — Mercedes claimed 'anti-stall activated'",
      "decision": {
        "penaltyPoints": 0,
        "timePenalty": 5,
        "gridPenalty": null,
        "driveThrough": false,
        "reprimand": false,
        "disqualified": false,
        "fine": null,
        "other": null
      },
      "document": "DOC-2025-038"
    },
    {
      "id": "INC-2025-040",
      "driverId": "lance-stroll",
      "teamId": "aston-martin",
      "round": 22,
      "season": 2025,
      "raceName": "Qatar Grand Prix",
      "date": "2025-11-30",
      "session": "Race",
      "incidentType": "causing-collision",
      "incidentDescription": "Caused collision with Alex Albon at Turn 1 on lap 22",
      "decision": {
        "penaltyPoints": 0,
        "timePenalty": 5,
        "gridPenalty": null,
        "driveThrough": false,
        "reprimand": false,
        "disqualified": false,
        "fine": null,
        "other": null
      },
      "document": "DOC-2025-040"
    },
    {
      "id": "INC-2025-039",
      "driverId": "oliver-bearman",
      "teamId": "haas",
      "round": 23,
      "season": 2025,
      "raceName": "Abu Dhabi Grand Prix",
      "date": "2025-12-07",
      "session": "Race",
      "incidentType": "change-of-direction",
      "incidentDescription": "Multiple changes of direction while defending against Stroll into Turn 6",
      "decision": {
        "penaltyPoints": 1,
        "timePenalty": 5,
        "gridPenalty": null,
        "driveThrough": false,
        "reprimand": false,
        "disqualified": false,
        "fine": null,
        "other": "Now at 10 points — 2 away from automatic race ban"
      },
      "document": "DOC-2025-039"
    },
    {
      "id": "INC-2025-041",
      "driverId": "liam-lawson",
      "teamId": "racing-bulls",
      "round": 23,
      "season": 2025,
      "raceName": "Abu Dhabi Grand Prix",
      "date": "2025-12-07",
      "session": "Race",
      "incidentType": "dangerous-driving",
      "incidentDescription": "Drove erratically in battle with Bearman at Turn 9 on lap 48",
      "decision": {
        "penaltyPoints": 1,
        "timePenalty": 5,
        "gridPenalty": null,
        "driveThrough": false,
        "reprimand": false,
        "disqualified": false,
        "fine": null,
        "other": null
      },
      "document": "DOC-2025-041"
    },
    {
      "id": "INC-2025-059",
      "driverId": "lance-stroll",
      "teamId": "aston-martin",
      "round": 23,
      "season": 2025,
      "raceName": "Abu Dhabi Grand Prix",
      "date": "2025-12-07",
      "session": "Race",
      "incidentType": "change-of-direction",
      "incidentDescription": "More than one change of position while defending",
      "decision": {
        "penaltyPoints": 1,
        "timePenalty": 5,
        "gridPenalty": null,
        "driveThrough": false,
        "reprimand": false,
        "disqualified": false,
        "fine": null,
        "other": null
      },
      "document": "DOC-2025-052"
    },
    {
      "id": "INC-2025-064",
      "driverId": "yuki-tsunoda",
      "teamId": "racing-bulls",
      "round": 23,
      "season": 2025,
      "raceName": "Abu Dhabi Grand Prix",
      "date": "2025-12-07",
      "session": "Race",
      "incidentType": "change-of-direction",
      "incidentDescription": "More than one change of position while defending",
      "decision": {
        "penaltyPoints": 1,
        "timePenalty": 5,
        "gridPenalty": null,
        "driveThrough": false,
        "reprimand": false,
        "disqualified": false,
        "fine": null,
        "other": null
      },
      "document": "DOC-2025-046"
    }
  ]
}
